[
	{
		"name": "Aul Satsang Vihar",
		"account": "SVAUL",
		"estd": "1988",
		"history": "Rev. Binkida visited here in several times",
		"address": "Vill/City .-Aul,P.O.- Aul, P.S.- Aul , \nDist.- KENDRAPARA ,  \nPIN- 754215 ,  Odisha , India \n",
		"contact": "+918763375188",
		"near": "Cuttack Rly. Stn./Aul Bus Stand/Bhubaneswar Airport",
		"details": "Work In Progress",
		"worker_contact": "Ramakanta Mishra(S) +918763375188",
		"other_workers_contact": "Dillip Kr. Saho(S) +919437332549",
		"abbreviations": "(S) - SPR, (I) - Incharge, (J) - Jajak, (A) - Adhurja"
	},
	{
		"name": "Rajakanika Satsang Vihar",
		"account": "",
		"estd": "1977",
		"history": "Inaugurated by Rev. Shipaida on 14th March 1997.",
		"address": "Vill/City .-Nahuni,P.O.- Pegarpara, P.S.- Rajakanika , \nDist.- KENDRAPARA ,  \nPIN- 754243 ,  Odisha , India \n",
		"contact": "+919938469983",
		"near": "Bhadrakh Rly Stn / Olaver Bus Stand / Bhubaneswar Airport",
		"details": "Acharyabhawan(2 rooms), Guesthouse(1 room).",
		"worker_contact": "Parsuram Manik(S)(I) +919938469983",
		"other_workers_contact": "Judhisthir Pradhan(S) +919938814090",
		"abbreviations": "(S) - SPR, (I) - Incharge, (J) - Jajak, (A) - Adhurja"
	}
]