[
	{
		"name": "Bidyapur Satsang Kendra",
		"account": "SKVDY",
		"estd": "9th July 2000",
		"history": "Inaugurated by Rev. Sejda on 22th December 2005",
		"address": "Vill/City .-Bidyapur,P.O.- Bidyapur, P.S.- Bongaigaon , \nDist.- BONGAIGAON ,  \nPIN- 783372 ,  Assam , India \n",
		"contact": "+919864636266",
		"near": "Bongaigaon Railway Station / Basugaone Bus Stand / Lokpriya Gopinath Bordoloi Airport",
		"details": "",
		"worker_contact": "Lalmohan Barman(J) +919864636266",
		"other_workers_contact": "Mathura Sutradhar +919954852104, Babul Singha +919678329926",
		"abbreviations": "(S) - SPR, (I) - Incharge, (J) - Jajak, (A) - Adhurja"
	},
	{
		"name": "Bongaigaon Satsang Vihar",
		"account": "SMBNG",
		"estd": "1974",
		"history": "VISITED BY SRI SRI BORDA ON 8.3.1979,ACHARYA DEV SRI SRI DADA ON 5.2.1985 AND ALSO VISITED BY MANY OTHER MEMBERS OF THAKUR FAMILY",
		"address": "Vill/City .-NATUNPARA,P.O.- BONGAIGAON, P.S.- BONGAIGAON , \nDist.- BONGAIGAON ,  \nPIN- 783380 ,  Assam , India \n",
		"contact": "9435194083",
		"near": "NEW BONGAIGAON RAILWAY STATION/BONGAIGAON BUS STOP",
		"details": "ACHARYA BHAWAN AND GUEST HOUSE WELL MAINTAINED",
		"worker_contact": "DEBABRATA SARMA(S)-9435194083",
		"other_workers_contact": "KRISHNA PRASAD KAKATI(S)-9435121464\r\nSRIKANTA GHOSH(S)-9435482290",
		"abbreviations": "(S) - SPR, (I) - Incharge, (J) - Jajak, (A) - Adhurja"
	},
	{
		"name": "Palengbari Satsang Kendra",
		"account": "",
		"estd": "26th January 1969",
		"history": "",
		"address": "Vill/City .-Palengbari,P.O.- Monakocha, P.S.- Palegbari , \nDist.- BONGAIGAON ,  \nPIN- 783391 ,  Assam , India \n",
		"contact": "",
		"near": "Palengbari Railway Station / Monakocha Bus Stand / Dibrugarh Airport",
		"details": "",
		"worker_contact": "",
		"other_workers_contact": "",
		"abbreviations": "(S) - SPR, (I) - Incharge, (J) - Jajak, (A) - Adhurja"
	},
	{
		"name": "Patildaha Satsang Kendra",
		"account": "SVPTL",
		"estd": "3rd Feb 1987.",
		"history": "Acharyadeb Sree Sree Dada Inaugurated the kendra on 3rd Feb 1987.",
		"address": "Vill/City .-Patildaha,P.O.- Patildaha , P.S.- Manikpur , \nDist.- BONGAIGAON ,  \nPIN- 783391 ,  Assam , India \n",
		"contact": "+919854463133",
		"near": "Patildaha Rly Stn / Patildaha Bus Stand / Guwahati Airport.",
		"details": "Acharyabhawan(1 room), Guesthouse(2 rooms).",
		"worker_contact": "Aswini Kr. Roy(S)(I) +919854463133",
		"other_workers_contact": "Jiten Chandra Das +919954716377,Kushendra Pathak +919854716377.",
		"abbreviations": "(S) - SPR, (I) - Incharge, (J) - Jajak, (A) - Adhurja"
	},
	{
		"name": "Uttar Salmara Satsang Kendra",
		"account": "SKUSL",
		"estd": "13th September 1987",
		"history": "Inaugurated by Rev. Binkida on 28th May 2009, Rev. Babaida Visited in several times.",
		"address": "Vill/City .-North Salmara,P.O.- North Salmara, P.S.- Abhayapuri , \nDist.- BONGAIGAON ,  \nPIN- 783383 ,  Assam , India \n",
		"contact": "+919957788748",
		"near": "Bongaigaon Railway Station / North salmara Bus Stand / Guwahati Airport",
		"details": "Achyra Bhawan(1rooms)\r\nGuest House(3rooms).",
		"worker_contact": "Herambo Prasad Medhi(S) +919577448539",
		"other_workers_contact": "Nibaran Ch.Sharma(S) +919917788748",
		"abbreviations": "(S) - SPR, (I) - Incharge, (J) - Jajak, (A) - Adhurja"
	}
]