[
	{
		"name": "Siwan Satsang Vihar",
		"account": "SVSWN",
		"estd": "1997",
		"history": "Inaugurated by Rev. Babaida.",
		"address": "Vill/City .-Siwan,P.O.- Siwan, P.S.- Siwan , \nDist.- SIWAN ,  \nPIN- 841226 ,  Bihar , India \n",
		"contact": "+919431218237",
		"near": "Kacheri Rly Stn / Lalit Bus Stand",
		"details": "Work in Progress.",
		"worker_contact": "Krishna Chandra Srivastava(S)(I) +91943128237",
		"other_workers_contact": "Rameswar Rai +919931421268, Vijay Kumar Prasad +919430404013.",
		"abbreviations": "(S) - SPR, (I) - Incharge, (J) - Jajak, (A) - Adhurja"
	}
]